classicexperiments/__init__.py
classicexperiments/experiment.py
classicexperiments-0.1.0a1.dist-info/LICENSE
classicexperiments-0.1.0a1.dist-info/METADATA
classicexperiments-0.1.0a1.dist-info/WHEEL
classicexperiments-0.1.0a1.dist-info/top_level.txt
classicexperiments-0.1.0a1.dist-info/RECORD
