Metadata-Version: 2.1
Name: classicexperiments
Version: 0.1.0a1
Summary: Persistent and reproducible experimental pipelines for Machine Learning
Home-page: https://github.com/jangop/classicexperiments
Author: Jan Philip Göpfert
Author-email: janphilip@gopfert.eu
License: UNKNOWN
Project-URL: Bug Reports, https://github.com/jangop/classicexperiments/issues
Project-URL: Source, https://github.com/jangop/classicexperiments
Keywords: machine learning
Platform: UNKNOWN
Classifier: Development Status :: 3 - Alpha
Classifier: Intended Audience :: Developers
Classifier: Topic :: Scientific/Engineering :: Artificial Intelligence
Classifier: Programming Language :: Python :: 3
Classifier: Programming Language :: Python :: 3.9
Classifier: License :: OSI Approved :: The Unlicense (Unlicense)
Requires-Python: >=3.9, <4
License-File: LICENSE
Requires-Dist: loguru
Requires-Dist: scikit-learn
Requires-Dist: numpy
Requires-Dist: appdirs
Requires-Dist: tabulate
Requires-Dist: more-termcolor
Requires-Dist: classicdata
Requires-Dist: tqdm
Provides-Extra: dev
Requires-Dist: check-manifest ; extra == 'dev'
Requires-Dist: black ; extra == 'dev'
Requires-Dist: pylint ; extra == 'dev'
Provides-Extra: test
Requires-Dist: coverage ; extra == 'test'
Requires-Dist: pytest ; extra == 'test'
Requires-Dist: black ; extra == 'test'
Requires-Dist: pylint ; extra == 'test'
